{"data":{"allMarkdownRemark":{"totalCount":1,"edges":[{"node":{"fields":{"slug":"/steganography/","date":"2015-05-02T00:00:00.000Z"},"excerpt":"There are many ways to conceal a message from untrusted entities, encryption is the far most used method for making sure no one but the…","timeToRead":3,"frontmatter":{"title":"Digital Steganography","tags":["Steganography"],"categories":["Steganography"],"date":"2015-05-02T00:00:00.000Z","template":"post"}}}]}},"pageContext":{"category":"Steganography"}}